LICENSE
MANIFEST.in
README.rst
setup.cfg
setup.py
tavern/__init__.py
tavern/core.py
tavern/entry.py
tavern/plugins.py
tavern/_plugins/__init__.py
tavern/_plugins/grpc/__init__.py
tavern/_plugins/grpc/client.py
tavern/_plugins/grpc/request.py
tavern/_plugins/grpc/response.py
tavern/_plugins/grpc/schema.yaml
tavern/_plugins/grpc/tavernhook.py
tavern/_plugins/mqtt/__init__.py
tavern/_plugins/mqtt/client.py
tavern/_plugins/mqtt/request.py
tavern/_plugins/mqtt/response.py
tavern/_plugins/mqtt/schema.yaml
tavern/_plugins/mqtt/tavernhook.py
tavern/_plugins/rest/__init__.py
tavern/_plugins/rest/request.py
tavern/_plugins/rest/response.py
tavern/_plugins/rest/tavernhook.py
tavern/request/__init__.py
tavern/request/base.py
tavern/response/__init__.py
tavern/response/base.py
tavern/schemas/__init__.py
tavern/schemas/extensions.py
tavern/schemas/files.py
tavern/schemas/tests.schema.yaml
tavern/testutils/__init__.py
tavern/testutils/helpers.py
tavern/testutils/jmesutils.py
tavern/testutils/pytesthook/__init__.py
tavern/testutils/pytesthook/error.py
tavern/testutils/pytesthook/file.py
tavern/testutils/pytesthook/hooks.py
tavern/testutils/pytesthook/item.py
tavern/testutils/pytesthook/newhooks.py
tavern/testutils/pytesthook/util.py
tavern/util/__init__.py
tavern/util/delay.py
tavern/util/dict_util.py
tavern/util/exceptions.py
tavern/util/general.py
tavern/util/jmespath_util.py
tavern/util/loader.py
tavern/util/python_2_util.py
tavern/util/retry.py
tavern_grpc.egg-info/PKG-INFO
tavern_grpc.egg-info/SOURCES.txt
tavern_grpc.egg-info/dependency_links.txt
tavern_grpc.egg-info/entry_points.txt
tavern_grpc.egg-info/requires.txt
tavern_grpc.egg-info/top_level.txt
tavern_grpc.egg-info/zip-safe